doccano_api_client/__init__.py
doccano_client_duydv-1.0.4.dist-info/LICENSE
doccano_client_duydv-1.0.4.dist-info/METADATA
doccano_client_duydv-1.0.4.dist-info/WHEEL
doccano_client_duydv-1.0.4.dist-info/top_level.txt
doccano_client_duydv-1.0.4.dist-info/RECORD
